pyHook/HookManager.py
pyHook/__init__.py
pyHook/_cpyHook.pyd
pyHook/aa hook.py
pyHook/cpyHook.py
pyHook/doc.py
pyHook/example.py
pyHook_3k_compiled-1.5.1.data/data/Lib/site-packages/pyHook/CHANGELOG.txt
pyHook_3k_compiled-1.5.1.data/data/Lib/site-packages/pyHook/LICENSE.txt
pyHook_3k_compiled-1.5.1.data/data/Lib/site-packages/pyHook/README.txt
pyHook_3k_compiled-1.5.1.dist-info/DESCRIPTION.rst
pyHook_3k_compiled-1.5.1.dist-info/METADATA
pyHook_3k_compiled-1.5.1.dist-info/RECORD
pyHook_3k_compiled-1.5.1.dist-info/WHEEL
pyHook_3k_compiled-1.5.1.dist-info/metadata.json
pyHook_3k_compiled-1.5.1.dist-info/top_level.txt
