Metadata-Version: 2.0
Name: pyHook-3k-compiled
Version: 1.5.1
Summary: pyHook: Python wrapper for out-of-context input hooks in Windows
Home-page: https://github.com/Answeror/pyhook_py3k
Author: Daniel Folkinshteyn
Author-email: nanotube@users.sf.net
License: http://www.opensource.org/licenses/mit-license.php
Download-URL: https://github.com/Answeror/pyhook_py3k
Platform: Win32
Classifier: Development Status :: 5 - Production/Stable
Classifier: Intended Audience :: Developers
Classifier: License :: OSI Approved :: MIT License
Classifier: Programming Language :: Python
Classifier: Topic :: System :: Monitoring
Classifier: Topic :: Software Development :: Libraries :: Python Modules
Classifier: Operating System :: Microsoft :: Windows
